gymtorax/__init__.py
gymtorax/action_handler.py
gymtorax/agents/__init__.py
gymtorax/agents/iter_hybrid_agent.py
gymtorax/agents/pid_agent.py
gymtorax/agents/random_agent.py
gymtorax/envs/__init__.py
gymtorax/envs/base_env.py
gymtorax/envs/iter_hybrid.json
gymtorax/envs/iter_hybrid_env.py
gymtorax/logger.py
gymtorax/observation_handler.py
gymtorax/rendering.py
gymtorax/rewards.py
gymtorax/torax_wrapper/__init__.py
gymtorax/torax_wrapper/config_loader.py
gymtorax/torax_wrapper/torax_app.py
gymtorax/torax_wrapper/torax_plot_helpers.py
gymtorax-1.0.0.dist-info/METADATA
gymtorax-1.0.0.dist-info/WHEEL
gymtorax-1.0.0.dist-info/licenses/LICENSE
gymtorax-1.0.0.dist-info/RECORD
