Metadata-Version: 2.4
Name: gymtorax
Version: 1.0.0
Summary: A Gymnasium environment for Torax simulations
License-File: LICENSE
Author: Antoine Mouchamps
Author-email: antoine.mouchamps@gmail.com
Requires-Python: >=3.10,<4.0
Classifier: Programming Language :: Python :: 3
Classifier: Programming Language :: Python :: 3.10
Classifier: Programming Language :: Python :: 3.11
Classifier: Programming Language :: Python :: 3.12
Classifier: Programming Language :: Python :: 3.13
Classifier: Programming Language :: Python :: 3.14
Requires-Dist: gymnasium (>=1.0.0,<2.0.0)
Requires-Dist: matplotlib (>=3.0.0,<4.0.0)
Requires-Dist: numpy (>=2.0.0,<3.0.0)
Requires-Dist: torax (==1.0.*)
Requires-Dist: xarray
